{
  "version": "5",
  "dialect": "pg",
  "id": "ee71b621-f33e-4bcf-9334-b06f5a68a955",
  "prevId": "19adceee-d3c1-4a15-ac95-ef930b6e4fb2",
  "tables": {
    "profiles": {
      "name": "profiles",
      "schema": "",
      "columns": {
        "id": {
          "name": "id",
          "type": "uuid",
          "primaryKey": true,
          "notNull": true,
          "default": "gen_random_uuid()"
        },
        "user_id": {
          "name": "user_id",
          "type": "uuid",
          "primaryKey": false,
          "notNull": false
        },
        "username": {
          "name": "username",
          "type": "varchar(256)",
          "primaryKey": false,
          "notNull": true
        },
        "display_name": {
          "name": "display_name",
          "type": "varchar(256)",
          "primaryKey": false,
          "notNull": true
        },
        "contact_email": {
          "name": "contact_email",
          "type": "varchar(256)",
          "primaryKey": false,
          "notNull": true
        },
        "profile_visibility": {
          "name": "profile_visibility",
          "type": "profile_visibility",
          "primaryKey": false,
          "notNull": true,
          "default": "'public'"
        },
        "profile_image_url": {
          "name": "profile_image_url",
          "type": "varchar(1024)",
          "primaryKey": false,
          "notNull": false
        },
        "cover_image_url": {
          "name": "cover_image_url",
          "type": "varchar(1024)",
          "primaryKey": false,
          "notNull": false
        },
        "headline": {
          "name": "headline",
          "type": "varchar(256)",
          "primaryKey": false,
          "notNull": false
        },
        "bio": {
          "name": "bio",
          "type": "text",
          "primaryKey": false,
          "notNull": false
        },
        "profession": {
          "name": "profession",
          "type": "varchar(128)",
          "primaryKey": false,
          "notNull": false
        },
        "job_title": {
          "name": "job_title",
          "type": "varchar(256)",
          "primaryKey": false,
          "notNull": false
        },
        "company": {
          "name": "company",
          "type": "varchar(256)",
          "primaryKey": false,
          "notNull": false
        },
        "profile_color": {
          "name": "profile_color",
          "type": "profile_color",
          "primaryKey": false,
          "notNull": false,
          "default": "'blue'"
        }
      },
      "indexes": {},
      "foreignKeys": {},
      "compositePrimaryKeys": {},
      "uniqueConstraints": {
        "profiles_contact_email_unique": {
          "name": "profiles_contact_email_unique",
          "nullsNotDistinct": false,
          "columns": [
            "contact_email"
          ]
        },
        "profile_username_unique": {
          "name": "profile_username_unique",
          "nullsNotDistinct": false,
          "columns": [
            "username"
          ]
        }
      }
    }
  },
  "enums": {
    "aal_level": {
      "name": "aal_level",
      "values": {
        "aal3": "aal3",
        "aal2": "aal2",
        "aal1": "aal1"
      }
    },
    "code_challenge_method": {
      "name": "code_challenge_method",
      "values": {
        "plain": "plain",
        "s256": "s256"
      }
    },
    "factor_status": {
      "name": "factor_status",
      "values": {
        "verified": "verified",
        "unverified": "unverified"
      }
    },
    "factor_type": {
      "name": "factor_type",
      "values": {
        "webauthn": "webauthn",
        "totp": "totp"
      }
    },
    "key_status": {
      "name": "key_status",
      "values": {
        "expired": "expired",
        "invalid": "invalid",
        "valid": "valid",
        "default": "default"
      }
    },
    "key_type": {
      "name": "key_type",
      "values": {
        "stream_xchacha20": "stream_xchacha20",
        "secretstream": "secretstream",
        "secretbox": "secretbox",
        "kdf": "kdf",
        "generichash": "generichash",
        "shorthash": "shorthash",
        "auth": "auth",
        "hmacsha256": "hmacsha256",
        "hmacsha512": "hmacsha512",
        "aead-det": "aead-det",
        "aead-ietf": "aead-ietf"
      }
    },
    "profile_color": {
      "name": "profile_color",
      "values": {
        "red": "red",
        "blue": "blue",
        "green": "green",
        "grape": "grape",
        "yellow": "yellow",
        "orange": "orange",
        "violet": "violet",
        "pink": "pink",
        "indigo": "indigo",
        "cyan": "cyan",
        "lime": "lime",
        "teal": "teal",
        "gray": "gray"
      }
    },
    "profile_visibility": {
      "name": "profile_visibility",
      "values": {
        "public": "public",
        "private": "private",
        "signed_in_users": "signed_in_users"
      }
    }
  },
  "schemas": {},
  "_meta": {
    "schemas": {},
    "tables": {},
    "columns": {}
  }
}